psi_toml/__init__.py
psi_toml/_version.py
psi_toml/parser.py
psi_toml/xxx.py
psi_toml-0.0.21.dist-info/WHEEL
psi_toml-0.0.21.dist-info/METADATA
psi_toml-0.0.21.dist-info/RECORD
