Metadata-Version: 2.3
Name: psi-toml
Version: 0.0.21
Summary: A very lite implementation of a toml parser, reader, and writer
Author: Jeff
Author-email: Jeff <jeffwatkins2000@gmail.com>
Requires-Dist: iniconfig>=2.1.0
Requires-Dist: packaging>=25.0
Requires-Dist: pluggy>=1.6.0
Requires-Dist: pygments>=2.19.2
Requires-Python: >=3.10, <3.13
